cmake_create_class.py
CMakeClassCreator/__init__.py
CMakeClassCreator/ast.py
CMakeClassCreator/class_inserter.py
CMakeClassCreator/list_item_string_path.py
CMakeClassCreator/parser.py
CMakeClassCreator/source_inserter.py
CMakeClassCreator/whitespace_inserter.py
CMake_Class_Creator-0.1.6.dist-info/LICENSE
CMake_Class_Creator-0.1.6.dist-info/METADATA
CMake_Class_Creator-0.1.6.dist-info/WHEEL
CMake_Class_Creator-0.1.6.dist-info/entry_points.txt
CMake_Class_Creator-0.1.6.dist-info/top_level.txt
CMake_Class_Creator-0.1.6.dist-info/RECORD
