Metadata-Version: 2.1
Name: CMake-Class-Creator
Version: 0.1.6
Summary: A script that inserts a new c++ class in an existing CMake configuration.
Home-page: https://github.com/FrankGoyens/CMakeClassCreator
Author: Frank Goyens
License: UNKNOWN
Platform: UNKNOWN
License-File: LICENSE
Requires-Dist: pyparsing (==3.0.2)
